django_db_constraints/__init__.py
django_db_constraints/apps.py
django_db_constraints/autodetector.py
django_db_constraints/operations.py
django_db_constraints-0.3.0.dist-info/DESCRIPTION.rst
django_db_constraints-0.3.0.dist-info/METADATA
django_db_constraints-0.3.0.dist-info/RECORD
django_db_constraints-0.3.0.dist-info/WHEEL
django_db_constraints-0.3.0.dist-info/metadata.json
django_db_constraints-0.3.0.dist-info/top_level.txt
