Metadata-Version: 1.0
Name: django-db-constraints
Version: 0.3.0
Summary: Add database table-level constraints to your Django model's Meta
Home-page: https://github.com/rapilabs/django-db-constraints
Author: shangxiao
Author-email: UNKNOWN
License: MIT
Platform: UNKNOWN
